client/__init__.py
client/bot.py
core/__init__.py
core/constants.py
dispatcher/__init__.py
dispatcher/dispatcher.py
types/__init__.py
types/message.py
utils/__init__.py
utils/exceptions.py
kabforge-0.1.3.dist-info/METADATA
kabforge-0.1.3.dist-info/WHEEL
kabforge-0.1.3.dist-info/top_level.txt
kabforge-0.1.3.dist-info/RECORD
